social_scraper/__init__.py
social_scraper/logging_config.py
social_scraper/models.py
social_scraper/reddit.py
social_scraper/twitter.py
social_scraper/utils.py
social_scraper_tool-0.11.0.dist-info/LICENCE
social_scraper_tool-0.11.0.dist-info/METADATA
social_scraper_tool-0.11.0.dist-info/WHEEL
social_scraper_tool-0.11.0.dist-info/RECORD
