Metadata-Version: 2.3
Name: social-scraper-tool
Version: 0.11.0
Summary: 
Author: H3NR1QU3M4LT4
Author-email: vlezyitalia@gmail.com
Requires-Python: >=3.10
Classifier: Programming Language :: Python :: 3
Classifier: Programming Language :: Python :: 3.10
Classifier: Programming Language :: Python :: 3.11
Classifier: Programming Language :: Python :: 3.12
Classifier: Programming Language :: Python :: 3.13
Requires-Dist: pandas (==2.2.0)
Requires-Dist: praw (==7.8.1)
Requires-Dist: twscrape (==0.11.1)
